{
  "teamId": "national-worldcup26-6719",
  "teamName": "Tunisia",
  "externalId": "6719",
  "ratingsVersion": "fc26-csv-20250921",
  "fetchedAt": "2026-07-11T05:31:03.291Z",
  "players": [
    {
      "id": "player-fotmob-national-worldcup26-6719-1131928",
      "externalId": "1131928",
      "name": "Mohamed Amine Ben Hmida",
      "overall": 80,
      "position": "DEF",
      "country": "Espérance",
      "countryCode": "es",
      "teamId": "national-worldcup26-6719",
      "photo": "https://images.fotmob.com/image_resources/playerimages/1131928.png",
      "number": 21
    },
    {
      "id": "player-fotmob-national-worldcup26-6719-574642",
      "externalId": "574642",
      "name": "Ellyes Skhiri",
      "overall": 80,
      "position": "MID",
      "country": "Eintracht Frankfurt",
      "countryCode": "ei",
      "teamId": "national-worldcup26-6719",
      "photo": "https://images.fotmob.com/image_resources/playerimages/574642.png",
      "number": 17
    },
    {
      "id": "player-fotmob-national-worldcup26-6719-566187",
      "externalId": "566187",
      "name": "Ali Abdi",
      "overall": 76,
      "position": "DEF",
      "country": "Nice",
      "countryCode": "ni",
      "teamId": "national-worldcup26-6719",
      "photo": "https://images.fotmob.com/image_resources/playerimages/566187.png",
      "number": 2
    },
    {
      "id": "player-fotmob-national-worldcup26-6719-304348",
      "externalId": "304348",
      "name": "Rani Khedira",
      "overall": 75,
      "position": "MID",
      "country": "Union Berlin",
      "countryCode": "un",
      "teamId": "national-worldcup26-6719",
      "photo": "https://images.fotmob.com/image_resources/playerimages/304348.png",
      "number": 13
    },
    {
      "id": "player-fotmob-national-worldcup26-6719-1113785",
      "externalId": "1113785",
      "name": "Hannibal Mejbri",
      "overall": 74,
      "position": "MID",
      "country": "Burnley",
      "countryCode": "bu",
      "teamId": "national-worldcup26-6719",
      "photo": "https://images.fotmob.com/image_resources/playerimages/1113785.png",
      "number": 10
    },
    {
      "id": "player-fotmob-national-worldcup26-6719-846392",
      "externalId": "846392",
      "name": "Montassar Talbi",
      "overall": 73,
      "position": "DEF",
      "country": "Lorient",
      "countryCode": "lo",
      "teamId": "national-worldcup26-6719",
      "photo": "https://images.fotmob.com/image_resources/playerimages/846392.png",
      "number": 3
    },
    {
      "id": "player-fotmob-national-worldcup26-6719-1244924",
      "externalId": "1244924",
      "name": "Ismaël Gharbi",
      "overall": 73,
      "position": "MID",
      "country": "Braga",
      "countryCode": "br",
      "teamId": "national-worldcup26-6719",
      "photo": "https://images.fotmob.com/image_resources/playerimages/1244924.png",
      "number": 11
    },
    {
      "id": "player-fotmob-national-worldcup26-6719-1015128",
      "externalId": "1015128",
      "name": "Elias Achouri",
      "overall": 72,
      "position": "MID",
      "country": "FC København",
      "countryCode": "fc",
      "teamId": "national-worldcup26-6719",
      "photo": "https://images.fotmob.com/image_resources/playerimages/1015128.png",
      "number": 7
    },
    {
      "id": "player-fotmob-national-worldcup26-6719-1285773",
      "externalId": "1285773",
      "name": "Elias Saad",
      "overall": 72,
      "position": "ATT",
      "country": "Augsburg",
      "countryCode": "au",
      "teamId": "national-worldcup26-6719",
      "photo": "https://images.fotmob.com/image_resources/playerimages/1285773.png",
      "number": 8
    },
    {
      "id": "player-fotmob-national-worldcup26-6719-789596",
      "externalId": "789596",
      "name": "Yan Valery",
      "overall": 71,
      "position": "DEF",
      "country": "Sheffield Wednesday",
      "countryCode": "sh",
      "teamId": "national-worldcup26-6719",
      "photo": "https://images.fotmob.com/image_resources/playerimages/789596.png",
      "number": 20
    },
    {
      "id": "player-fotmob-national-worldcup26-6719-982855",
      "externalId": "982855",
      "name": "Aymen Dahmen",
      "overall": 70,
      "position": "GK",
      "country": "CS Sfaxien",
      "countryCode": "cs",
      "teamId": "national-worldcup26-6719",
      "photo": "https://images.fotmob.com/image_resources/playerimages/982855.png",
      "number": 16
    },
    {
      "id": "player-fotmob-national-worldcup26-6719-1160097",
      "externalId": "1160097",
      "name": "Omar Rekik",
      "overall": 70,
      "position": "DEF",
      "country": "Maribor",
      "countryCode": "ma",
      "teamId": "national-worldcup26-6719",
      "photo": "https://images.fotmob.com/image_resources/playerimages/1160097.png",
      "number": 4
    },
    {
      "id": "player-fotmob-national-worldcup26-6719-1311408",
      "externalId": "1311408",
      "name": "Hazem Mastouri",
      "overall": 70,
      "position": "ATT",
      "country": "Dynamo Makhachkala",
      "countryCode": "dy",
      "teamId": "national-worldcup26-6719",
      "photo": "https://images.fotmob.com/image_resources/playerimages/1311408.png",
      "number": 9
    },
    {
      "id": "player-fotmob-national-worldcup26-6719-712132",
      "externalId": "712132",
      "name": "Mortadha Ben Ouanes",
      "overall": 69,
      "position": "ATT",
      "country": "Kasımpaşa",
      "countryCode": "ka",
      "teamId": "national-worldcup26-6719",
      "photo": "https://images.fotmob.com/image_resources/playerimages/712132.png",
      "number": 21
    },
    {
      "id": "player-fotmob-national-worldcup26-6719-921919",
      "externalId": "921919",
      "name": "Sebastian Tounekti",
      "overall": 69,
      "position": "ATT",
      "country": "Celtic",
      "countryCode": "ce",
      "teamId": "national-worldcup26-6719",
      "photo": "https://images.fotmob.com/image_resources/playerimages/921919.png",
      "number": 26
    },
    {
      "id": "player-fotmob-national-worldcup26-6719-543363",
      "externalId": "543363",
      "name": "Sabri Ben Hassen",
      "overall": 68,
      "position": "GK",
      "country": "Etoile du Sahel",
      "countryCode": "et",
      "teamId": "national-worldcup26-6719",
      "photo": "https://images.fotmob.com/image_resources/playerimages/543363.png",
      "number": 28
    },
    {
      "id": "player-fotmob-national-worldcup26-6719-771686",
      "externalId": "771686",
      "name": "Dylan Bronn",
      "overall": 68,
      "position": "DEF",
      "country": "Servette",
      "countryCode": "se",
      "teamId": "national-worldcup26-6719",
      "photo": "https://images.fotmob.com/image_resources/playerimages/771686.png",
      "number": 6
    },
    {
      "id": "player-fotmob-national-worldcup26-6719-1131896",
      "externalId": "1131896",
      "name": "Hadj Mahmoud",
      "overall": 68,
      "position": "MID",
      "country": "Tunisia",
      "countryCode": "tu",
      "teamId": "national-worldcup26-6719",
      "photo": "https://images.fotmob.com/image_resources/playerimages/1131896.png",
      "number": 15
    },
    {
      "id": "player-fotmob-national-worldcup26-6719-1685596",
      "externalId": "1685596",
      "name": "Rayan Elloumi",
      "overall": 68,
      "position": "ATT",
      "country": "Vancouver Whitecaps",
      "countryCode": "va",
      "teamId": "national-worldcup26-6719",
      "photo": "https://images.fotmob.com/image_resources/playerimages/1685596.png",
      "number": 18
    },
    {
      "id": "player-fotmob-national-worldcup26-6719-845336",
      "externalId": "845336",
      "name": "Firas Chaouat",
      "overall": 68,
      "position": "ATT",
      "country": "Club Africain",
      "countryCode": "cl",
      "teamId": "national-worldcup26-6719",
      "photo": "https://images.fotmob.com/image_resources/playerimages/845336.png",
      "number": 19
    },
    {
      "id": "player-fotmob-national-worldcup26-6719-1055316",
      "externalId": "1055316",
      "name": "Anis Ben Slimane",
      "overall": 67,
      "position": "MID",
      "country": "Norwich City",
      "countryCode": "no",
      "teamId": "national-worldcup26-6719",
      "photo": "https://images.fotmob.com/image_resources/playerimages/1055316.png",
      "number": 25
    },
    {
      "id": "player-fotmob-national-worldcup26-6719-1413151",
      "externalId": "1413151",
      "name": "Moutaz Neffati",
      "overall": 63,
      "position": "DEF",
      "country": "IFK Norrköping",
      "countryCode": "if",
      "teamId": "national-worldcup26-6719",
      "photo": "https://images.fotmob.com/image_resources/playerimages/1413151.png",
      "number": 23
    },
    {
      "id": "player-fotmob-national-worldcup26-6719-1797902",
      "externalId": "1797902",
      "name": "Adem Arous",
      "overall": 59,
      "position": "DEF",
      "country": "Kasımpaşa",
      "countryCode": "ka",
      "teamId": "national-worldcup26-6719",
      "photo": "https://images.fotmob.com/image_resources/playerimages/1797902.png",
      "number": 24
    }
  ]
}